m_recommender/__init__.py
m_recommender/memory.py
memory_recommender-0.0.4.dist-info/LICENSE
memory_recommender-0.0.4.dist-info/METADATA
memory_recommender-0.0.4.dist-info/WHEEL
memory_recommender-0.0.4.dist-info/top_level.txt
memory_recommender-0.0.4.dist-info/RECORD
