Metadata-Version: 2.1
Name: memory-recommender
Version: 0.0.4
Summary: A memory-based recommender system
Home-page: https://github.com/k-w-lee/
Author: Morris Lee
Author-email: info.leekahwin@gmail.com
Project-URL: Bug Tracker, https://github.com/k-w-lee/
Classifier: Programming Language :: Python :: 3
Classifier: License :: OSI Approved :: MIT License
Classifier: Operating System :: OS Independent
Requires-Python: >=3.6
License-File: LICENSE
